zenable_mcp/__init__.py
zenable_mcp/__main__.py
zenable_mcp/cli_managers.py
zenable_mcp/client.py
zenable_mcp/constants.py
zenable_mcp/exceptions.py
zenable_mcp/exit_codes.py
zenable_mcp/file_discovery.py
zenable_mcp/ide_config.py
zenable_mcp/ide_context.py
zenable_mcp/platform_strategies.py
zenable_mcp/version_check.py
zenable_mcp/checkpoint/__init__.py
zenable_mcp/checkpoint/models.py
zenable_mcp/checkpoint/storage.py
zenable_mcp/commands/__init__.py
zenable_mcp/commands/check.py
zenable_mcp/commands/doctor.py
zenable_mcp/commands/hook.py
zenable_mcp/commands/login.py
zenable_mcp/commands/logout.py
zenable_mcp/commands/logs.py
zenable_mcp/commands/version.py
zenable_mcp/commands/install/__init__.py
zenable_mcp/commands/install/command_generator.py
zenable_mcp/commands/install/hook.py
zenable_mcp/commands/install/mcp.py
zenable_mcp/hook_input_handlers/__init__.py
zenable_mcp/hook_input_handlers/base.py
zenable_mcp/hook_input_handlers/claude_code.py
zenable_mcp/hook_input_handlers/cursor.py
zenable_mcp/hook_input_handlers/kiro.py
zenable_mcp/hook_input_handlers/registry.py
zenable_mcp/hook_input_handlers/windsurf.py
zenable_mcp/logging/__init__.py
zenable_mcp/logging/command_logger.py
zenable_mcp/logging/local_logger.py
zenable_mcp/logging/logged_echo.py
zenable_mcp/logging/logging_config.py
zenable_mcp/logging/logging_handler.py
zenable_mcp/logging/persona.py
zenable_mcp/models/__init__.py
zenable_mcp/models/claude_hook_input.py
zenable_mcp/models/hook_config.py
zenable_mcp/models/legacy_mcp_config.py
zenable_mcp/models/mcp_config.py
zenable_mcp/usage/__init__.py
zenable_mcp/usage/fingerprint.py
zenable_mcp/usage/manager.py
zenable_mcp/usage/models.py
zenable_mcp/usage/sender.py
zenable_mcp/user_config/__init__.py
zenable_mcp/user_config/config_handler.py
zenable_mcp/user_config/config_handler_factory.py
zenable_mcp/user_config/config_parser.py
zenable_mcp/user_config/data_models.py
zenable_mcp/utils/__init__.py
zenable_mcp/utils/cli_validators.py
zenable_mcp-2.30.0.dist-info/licenses/LICENSE
zenable_mcp-2.30.0.dist-info/METADATA
zenable_mcp-2.30.0.dist-info/WHEEL
zenable_mcp-2.30.0.dist-info/entry_points.txt
zenable_mcp-2.30.0.dist-info/top_level.txt
zenable_mcp-2.30.0.dist-info/RECORD
