Metadata-Version: 2.4
Name: zenable_mcp
Version: 2.30.0
Summary: MCP client for Zenable conformance checking
Author-email: Zenable <Python@zenable.io>
License: Proprietary
Project-URL: Homepage, https://zenable.io
Project-URL: Documentation, https://docs.zenable.io/
Project-URL: Issues, https://zenable.io/feedback
Keywords: mcp,claude,hooks,conformance,zenable,code-quality,security,compliance,policy-as-code,specifications,spec-driven-development
Classifier: Development Status :: 3 - Alpha
Classifier: Intended Audience :: Developers
Classifier: License :: Other/Proprietary License
Classifier: Operating System :: OS Independent
Classifier: Programming Language :: Python :: 3
Classifier: Programming Language :: Python :: 3.11
Classifier: Programming Language :: Python :: 3.12
Classifier: Programming Language :: Python :: 3.13
Classifier: Programming Language :: Python :: 3.14
Requires-Python: >=3.11
License-File: LICENSE
Requires-Dist: click>=8
Requires-Dist: fastmcp<2.14.0,>=2.13.0
Requires-Dist: gitpython>=3.1
Requires-Dist: httpx>=0.28
Requires-Dist: json5>=0.12
Requires-Dist: py-key-value-aio[disk]>=0.2.8
Requires-Dist: pydantic>=2.12
Requires-Dist: pyyaml>=6.0.3
Requires-Dist: requests>=2.32
Requires-Dist: textual>=0.86.0
Requires-Dist: tomlkit
Dynamic: license-file
